{
  "lastUpdated": "2026-06-21T10:48:45.297Z",
  "trafficLeaderboard": [
    {
      "rank": 1,
      "site": "Trending Cultural Narrative Thread Pool #1",
      "category": "Social Pulse",
      "dailyHits": "3599 Coms",
      "growth": "+31 up/min",
      "trend": "Viral discussion megathread running hot across aggregated open networks.",
      "url": "https://www.reddit.com/r/popular/"
    },
    {
      "rank": 2,
      "site": "Trending Cultural Narrative Thread Pool #2",
      "category": "Social Pulse",
      "dailyHits": "3883 Coms",
      "growth": "+27 up/min",
      "trend": "Viral discussion megathread running hot across aggregated open networks.",
      "url": "https://www.reddit.com/r/popular/"
    },
    {
      "rank": 3,
      "site": "Trending Cultural Narrative Thread Pool #3",
      "category": "Social Pulse",
      "dailyHits": "2717 Coms",
      "growth": "+36 up/min",
      "trend": "Viral discussion megathread running hot across aggregated open networks.",
      "url": "https://www.reddit.com/r/popular/"
    },
    {
      "rank": 4,
      "site": "Trending Cultural Narrative Thread Pool #4",
      "category": "Social Pulse",
      "dailyHits": "2294 Coms",
      "growth": "+38 up/min",
      "trend": "Viral discussion megathread running hot across aggregated open networks.",
      "url": "https://www.reddit.com/r/popular/"
    },
    {
      "rank": 5,
      "site": "Macro Economic Index Data Release Analysis",
      "category": "Finance Trends",
      "dailyHits": "368 Traders",
      "growth": "+7 coms/min",
      "trend": "High-velocity macroeconomic assessment. Market-moving community analysis parsing live execution metrics.",
      "url": "https://www.reddit.com/r/stocks/"
    },
    {
      "rank": 6,
      "site": "Options Chain Implied Volatility Shift",
      "category": "Finance Trends",
      "dailyHits": "480 Traders",
      "growth": "-10 coms/min",
      "trend": "High-velocity macroeconomic assessment. Market-moving community analysis parsing live execution metrics.",
      "url": "https://www.reddit.com/r/stocks/"
    },
    {
      "rank": 7,
      "site": "Tech Sector Earnings Report Breakdown",
      "category": "Finance Trends",
      "dailyHits": "470 Traders",
      "growth": "-13 coms/min",
      "trend": "High-velocity macroeconomic assessment. Market-moving community analysis parsing live execution metrics.",
      "url": "https://www.reddit.com/r/stocks/"
    },
    {
      "rank": 8,
      "site": "Treasury Yield Yield-Curve Movement",
      "category": "Finance Trends",
      "dailyHits": "437 Traders",
      "growth": "-18 coms/min",
      "trend": "High-velocity macroeconomic assessment. Market-moving community analysis parsing live execution metrics.",
      "url": "https://www.reddit.com/r/stocks/"
    },
    {
      "rank": 9,
      "site": "john alite",
      "category": "Popular Searches",
      "dailyHits": "200+",
      "growth": "+6.0%",
      "trend": "New Jersey council member, who previously admitted to several murders, arrested for extortion",
      "url": "https://www.cbsnews.com/news/john-alite-arrested-new-jersey-gotti-gambino-mob-extortion/"
    },
    {
      "rank": 10,
      "site": "cathie wood ark invest sales",
      "category": "Popular Searches",
      "dailyHits": "2000+",
      "growth": "+10.1%",
      "trend": "Cathie Wood buys $52 million of surging tech stock",
      "url": "https://www.thestreet.com/investing/stocks/cathie-wood-buys-52-million-of-surging-tech-stock"
    },
    {
      "rank": 11,
      "site": "diane parry",
      "category": "Popular Searches",
      "dailyHits": "200+",
      "growth": "+9.4%",
      "trend": "Licensable picture: Seawall at Midtown Beach Thursday morning June 18, 2026.",
      "url": "https://www.reutersconnect.com/item/seawall-at-midtown-beach-thursday-morning-june-18-2026/dGFnOnJldXRlcnMuY29tLDIwMjY6bmV3c21sX01UMVVTQVRPREFZMjkyMjIwNjQ"
    },
    {
      "rank": 12,
      "site": "community",
      "category": "Popular Searches",
      "dailyHits": "500+",
      "growth": "+10.8%",
      "trend": "DOJ memo stokes fear among disability advocates of a return to institutionalization",
      "url": "https://www.npr.org/2026/06/20/nx-s1-5865100/doj-memo-trump-disability-civil-rights-institutionalization"
    }
  ]
}